dgarbsutils/Cloudwatch.py
dgarbsutils/DynamoDB.py
dgarbsutils/EventBridge.py
dgarbsutils/GraphMail.py
dgarbsutils/__init__.py
dgarbsutils/awsUtils.py
dgarbsutils/utils.py
dgarbsutils-1.6.2.dist-info/LICENSE
dgarbsutils-1.6.2.dist-info/METADATA
dgarbsutils-1.6.2.dist-info/WHEEL
dgarbsutils-1.6.2.dist-info/top_level.txt
dgarbsutils-1.6.2.dist-info/RECORD
