Metadata-Version: 2.1
Name: dgarbsutils
Version: 1.6.2
Summary: A set of curated utils
Home-page: https://github.com/dgarbalo/py-utils
Author: Devon Garbalosa
Author-email: dgarbalo@gmail.com
Project-URL: Bug Tracker, https://github.com/dgarbalo/py-utils/issues
Classifier: Programming Language :: Python :: 3
Classifier: License :: OSI Approved :: MIT License
Classifier: Operating System :: OS Independent
Requires-Python: >=3.7
License-File: LICENSE
Requires-Dist: boto3
Requires-Dist: botocore
Requires-Dist: psycopg2-binary
